musicscript/__init__.py
musicscript/album.py
musicscript/download.py
musicscript/lyrics.py
musicscript/metadata.py
musicscript/print_runner.py
musicscript/program_runner.py
musicscript/runner.py
musicscript/song.py
musicscript/utils.py
musicscript-0.2.0.dist-info/METADATA
musicscript-0.2.0.dist-info/WHEEL
musicscript-0.2.0.dist-info/entry_points.txt
musicscript-0.2.0.dist-info/RECORD
