Metadata-Version: 2.4
Name: musicscript
Version: 0.2.0
Summary: Add your description here
Author-email: Meek Msaki <98189596+mmsaki@users.noreply.github.com>
Requires-Python: >=3.9
Requires-Dist: beautifulsoup4>=4.12.3
Requires-Dist: pytest>=8.3.4
Requires-Dist: requests>=2.32.3
Requires-Dist: ruff>=0.8.3
Requires-Dist: unidecode>=1.3.8
